ua_generic_rest_api/__init__.py
ua_generic_rest_api/tests/test_generic_rest_api.py
ua_generic_rest_api/ua_generic_rest_api.py
ua_generic_rest_api-2.0.6.dist-info/LICENSE
ua_generic_rest_api-2.0.6.dist-info/METADATA
ua_generic_rest_api-2.0.6.dist-info/WHEEL
ua_generic_rest_api-2.0.6.dist-info/RECORD
