Metadata-Version: 2.1
Name: ua-generic-rest-api
Version: 2.0.6
Summary: Provides basic REST API Implementation for GET, PUT, and POST, and DELETE.
Author: Your Name
Author-email: you@example.com
Requires-Python: >=3.11,<4.0
Classifier: Programming Language :: Python :: 3
Classifier: Programming Language :: Python :: 3.11
Classifier: Programming Language :: Python :: 3.12
Requires-Dist: requests (>=2.31.0,<3.0.0)
